sl5api/__init__.py
sl5api/main.py
sl5api/rootcert.py
sl5api/pb/__init__.py
sl5api/pb/sl5_api_pb2.py
sl5api/pb/sl5_api_pb2.pyi
sl5api/pb/sl5_api_pb2_grpc.py
sl5api-0.0.7.dist-info/METADATA
sl5api-0.0.7.dist-info/WHEEL
sl5api-0.0.7.dist-info/licenses/LICENSE
sl5api-0.0.7.dist-info/RECORD
