Metadata-Version: 2.4
Name: sl5api
Version: 0.0.7
Summary: SimpLight SCADA v5 gRPC api
Author-email: SimpLight <simp@simplight.ru>
License-Expression: MIT
License-File: LICENSE
Classifier: Operating System :: OS Independent
Classifier: Programming Language :: Python :: 3
Requires-Python: >=3.9
Requires-Dist: grpcio>=1.76.0
Requires-Dist: protobuf>=6.33.2
